[
  {
    "id": 1773501227365,
    "title": "2",
    "thumbnail": "https://picsum.photos/seed/1773501227365/640/360",
    "streamer": "уѕгУЎФ",
    "viewers": 0,
    "isLive": false,
    "isLocal": true,
    "videoUrl": "/courses/1773501227365.mp4",
    "price": 0,
    "category": "уѕгУЎФ"
  },
  {
    "id": 1773501056194,
    "title": "1",
    "thumbnail": "https://picsum.photos/seed/1773501056194/640/360",
    "streamer": "уѕгУЎФ",
    "viewers": 0,
    "isLive": false,
    "isLocal": true,
    "videoUrl": "/courses/1773501056194.mp4",
    "price": 0,
    "category": "уѕгУЎФ"
  }
]